{
  "posts": [
    {
      "firstname": "demo",
      "lastname": "demo",
      "birthdate": "2023-04-11T18:30:00.000Z",
      "gender": "f",
      "education": "HSC",
      "company": "demo",
      "jobExperience": 0,
      "salary": 0,
      "id": 1
    },
    {
      "firstname": "zebra",
      "lastname": "don",
      "birthdate": "2023-04-18T18:30:00.000Z",
      "gender": "m",
      "education": "Post Graduate",
      "company": "apple",
      "jobExperience": 0,
      "salary": 29,
      "id": 2
    }
  ],
  "comments": [],
  "profile": {
    "name": "typicode"
  }
}